numba_integrators/_API.py
numba_integrators/__init__.py
numba_integrators/__main__.py
numba_integrators/_advanced.py
numba_integrators/_aux.py
numba_integrators/_basic.py
numba_integrators/_structref.py
numba_integrators/_structref_builder.py
numba_integrators/_structref_generated.py
numba_integrators/py.typed
numba_integrators/reference.py
numba_integrators-0.3.1.dist-info/LICENSE
numba_integrators-0.3.1.dist-info/METADATA
numba_integrators-0.3.1.dist-info/WHEEL
numba_integrators-0.3.1.dist-info/entry_points.txt
numba_integrators-0.3.1.dist-info/top_level.txt
numba_integrators-0.3.1.dist-info/RECORD
