Metadata-Version: 2.1
Name: numba-integrators
Version: 0.3.1
Summary: Numerical integrators using Numba
Author: Limespy
Project-URL: Homepage, https://github.com/Limespy/numba-integrators
Project-URL: Changelog, https://github.com/Limespy/numba-integrators/blob/main/README.md#Changelog
Project-URL: Issue Tracker, https://github.com/Limespy/numba-integrators/issues
Classifier: Development Status :: 3 - Alpha
Classifier: License :: OSI Approved :: MIT License
Classifier: Operating System :: Unix
Classifier: Operating System :: POSIX
Classifier: Operating System :: Microsoft :: Windows
Classifier: Programming Language :: Python :: 3
Classifier: Programming Language :: Python :: 3 :: Only
Classifier: Programming Language :: Python :: 3.10
Classifier: Programming Language :: Python :: 3.11
Classifier: Programming Language :: Python :: 3.12
Requires-Python: >=3.10
License-File: LICENSE
Requires-Dist: limedev >=0.6.1
Requires-Dist: numba >=0.57.0
Requires-Dist: numpy >=1.24.3
Requires-Dist: scipy >=1.11.1
Provides-Extra: build
Requires-Dist: limedev[package] >=0.6.1 ; extra == 'build'
Provides-Extra: dev
Requires-Dist: limedev[package,readme,test] >=0.6.1 ; extra == 'dev'
Requires-Dist: pre-commit >=3.2.2 ; extra == 'dev'
Requires-Dist: tox >=4.5.1 ; extra == 'dev'
